{
  "schemaVersion": 2,
  "$schema": "https://schemas.runtipi.io/dynamic-compose.json",
  "services": [
    {
      "name": "music-assistant",
      "image": "ghcr.io/music-assistant/server:2.7.0",
      "internalPort": 8095,
      "isMain": true,
      "networkMode": "host",
      "volumes": [
        {
          "hostPath": "${APP_DATA_DIR}/data/musicassistant",
          "containerPath": "/data"
        },
        {
          "hostPath": "${APP_DATA_DIR}/data/media",
          "containerPath": "/media"
        }
      ],
      "environment": [
        {
          "key": "TZ",
          "value": "Europe/Paris"
        }
      ],
      "restart": "unless-stopped"
    }
  ]
}
